la_nlp/__init__.py
la_nlp/components.py
la_nlp/scratch.py
la_nlp/scratch2.py
la_nlp/utils.py
la_nlp/data/aspects.toml
la_nlp/pipes/__init__.py
la_nlp/pipes/aspect_sentiment.py
tests/test_aspect_sentiment.py
tests/test_components.py
tests/test_utils.py
la_nlp-0.5.0.dist-info/LICENSE
la_nlp-0.5.0.dist-info/METADATA
la_nlp-0.5.0.dist-info/WHEEL
la_nlp-0.5.0.dist-info/top_level.txt
la_nlp-0.5.0.dist-info/RECORD
